{"full_name":["Hugh Davies"],"label":["Hugh Davies || DEF || $119.90K"],"tick_interval":[0.01],"daily_increase_x":[20475],"daily_increase_y":[0.08],"daily_increase_text":["Snapshot Date: 2026-01-23<br />Change In Adjusted Ownership: 0.08%<br />Change In Raw Ownership (Official):0.0681515%<br />Change Team completion: 83.2%"],"daily_decrease_x":[20476,20477,20478,20479],"daily_decrease_y":[0,0,0,0],"daily_decrease_y_abs":[-0,-0,-0,-0],"daily_decrease_text":["Snapshot Date: 2026-01-24<br />Change In Adjusted Ownership: 0%<br />Change In Raw Ownership (Official):-0.0046129%<br />Change Team completion: 0.9%","Snapshot Date: 2026-01-25<br />Change In Adjusted Ownership: 0%<br />Change In Raw Ownership (Official):0.0034252%<br />Change Team completion: 0.2%","Snapshot Date: 2026-01-26<br />Change In Adjusted Ownership: 0%<br />Change In Raw Ownership (Official):-0.00324380000000001%<br />Change Team completion: 0.7%","Snapshot Date: 2026-01-27<br />Change In Adjusted Ownership: 0%<br />Change In Raw Ownership (Official):0.00220480000000001%<br />Change Team completion: 0.3%"],"snapshot_x":[20475,20476,20477,20478,20479],"snapshot_y":[0.08,0.08,0.08,0.08,0.08],"snapshot_text":["Snapshot Date: 2026-01-23<br />Ownership (Adjusted): 0.08%<br />Raw Ownership (Official): 0.07%<br />Team completion: 83.2%","Snapshot Date: 2026-01-24<br />Ownership (Adjusted): 0.08%<br />Raw Ownership (Official): 0.06%<br />Team completion: 84.1%","Snapshot Date: 2026-01-25<br />Ownership (Adjusted): 0.08%<br />Raw Ownership (Official): 0.07%<br />Team completion: 84.3%","Snapshot Date: 2026-01-26<br />Ownership (Adjusted): 0.08%<br />Raw Ownership (Official): 0.06%<br />Team completion: 85%","Snapshot Date: 2026-01-27<br />Ownership (Adjusted): 0.08%<br />Raw Ownership (Official): 0.07%<br />Team completion: 85.2%"]}
