{"full_name":["Griffin Logue"],"label":["Griffin Logue || DEF || $336.20K"],"tick_interval":[0.01],"daily_increase_x":[20475],"daily_increase_y":[0.05],"daily_increase_text":["Snapshot Date: 2026-01-23<br />Change In Adjusted Ownership: 0.05%<br />Change In Raw Ownership (Official):0.0408909%<br />Change Team completion: 83.2%"],"daily_decrease_x":[20476,20477,20478,20479,20480],"daily_decrease_y":[-0.01,0,0,0,-0.01],"daily_decrease_y_abs":[0.01,-0,-0,-0,0.01],"daily_decrease_text":["Snapshot Date: 2026-01-24<br />Change In Adjusted Ownership: -0.01%<br />Change In Raw Ownership (Official):-0.004234%<br />Change Team completion: 0.9%","Snapshot Date: 2026-01-25<br />Change In Adjusted Ownership: 0%<br />Change In Raw Ownership (Official):-0.0043296%<br />Change Team completion: 0.2%","Snapshot Date: 2026-01-26<br />Change In Adjusted Ownership: 0%<br />Change In Raw Ownership (Official):-0.000467300000000004%<br />Change Team completion: 0.7%","Snapshot Date: 2026-01-27<br />Change In Adjusted Ownership: 0%<br />Change In Raw Ownership (Official):-0.0018942%<br />Change Team completion: 0.3%","Snapshot Date: 2026-01-28<br />Change In Adjusted Ownership: -0.01%<br />Change In Raw Ownership (Official):-0.000122199999999999%<br />Change Team completion: 0%"],"snapshot_x":[20475,20476,20477,20478,20479,20480],"snapshot_y":[0.05,0.04,0.04,0.04,0.04,0.03],"snapshot_text":["Snapshot Date: 2026-01-23<br />Ownership (Adjusted): 0.05%<br />Raw Ownership (Official): 0.04%<br />Team completion: 83.2%","Snapshot Date: 2026-01-24<br />Ownership (Adjusted): 0.04%<br />Raw Ownership (Official): 0.04%<br />Team completion: 84.1%","Snapshot Date: 2026-01-25<br />Ownership (Adjusted): 0.04%<br />Raw Ownership (Official): 0.03%<br />Team completion: 84.3%","Snapshot Date: 2026-01-26<br />Ownership (Adjusted): 0.04%<br />Raw Ownership (Official): 0.03%<br />Team completion: 85%","Snapshot Date: 2026-01-27<br />Ownership (Adjusted): 0.04%<br />Raw Ownership (Official): 0.03%<br />Team completion: 85.2%","Snapshot Date: 2026-01-28<br />Ownership (Adjusted): 0.03%<br />Raw Ownership (Official): 0.03%<br />Team completion: 85.3%"]}
